msp/__init__.py
msp/message_ids.py
msp/multiwii.py
msp/data_structures/__init__.py
msp/data_structures/altitude.py
msp/data_structures/analog.py
msp/data_structures/attitude.py
msp/data_structures/box.py
msp/data_structures/box_ids.py
msp/data_structures/box_names.py
msp/data_structures/channels.py
msp/data_structures/comp_gps.py
msp/data_structures/data_structure.py
msp/data_structures/gps.py
msp/data_structures/identification.py
msp/data_structures/imus.py
msp/data_structures/misc.py
msp/data_structures/motor_pins.py
msp/data_structures/motors.py
msp/data_structures/pid_coefficients.py
msp/data_structures/pid_names.py
msp/data_structures/rc_tuning.py
msp/data_structures/servo_config.py
msp/data_structures/servos.py
msp/data_structures/status.py
msp/data_structures/wp.py
msp_python3-0.4.0.dist-info/LICENSE
msp_python3-0.4.0.dist-info/METADATA
msp_python3-0.4.0.dist-info/WHEEL
msp_python3-0.4.0.dist-info/top_level.txt
msp_python3-0.4.0.dist-info/RECORD
