Metadata-Version: 2.1
Name: msp-python3
Version: 0.4.0
Summary: MultiWii Serial Protocol (MSP) API for python3
Home-page: https://github.com/LukeARohl/MSP-Python3
Author: Luke A. Rohl
Author-email: Luke.A.Rohl@gmail.com
License: MIT
Platform: UNKNOWN
Classifier: Programming Language :: Python :: 3
Classifier: License :: OSI Approved :: MIT License
Classifier: Operating System :: OS Independent
Classifier: Development Status :: 2 - Pre-Alpha
Requires-Python: >=3.5
Requires-Dist: pyserial
